schema_jobs/__init__.py
schema_jobs/jobs/__init__.py
schema_jobs/jobs/configuration/__init__.py
schema_jobs/jobs/configuration/database_configuration.py
schema_jobs/jobs/configuration/table_configs.py
schema_jobs/jobs/deploy/__init__.py
schema_jobs/jobs/deploy/deploy_database_tables.py
schema_jobs/jobs/migration/__init__.py
schema_jobs/jobs/migration/deploy_migration.py
schema_jobs/jobs/utility/__init__.py
schema_jobs/jobs/utility/schema/__init__.py
schema_jobs/jobs/utility/schema/database.py
schema_jobs/jobs/utility/schema/migration.py
schema_jobs/jobs/utility/schema/schemas.py
schema_jobs/jobs/utility/schema/sql.py
schema_jobs/jobs/utility/schema/table.py
schema_jobs-0.1.15.dist-info/METADATA
schema_jobs-0.1.15.dist-info/WHEEL
schema_jobs-0.1.15.dist-info/RECORD
