Metadata-Version: 2.1
Name: schema-jobs
Version: 0.1.15
Summary: 
Author: Brian L
Author-email: bclipp770@gmail.com
Requires-Python: >=3.9,<4.0
Classifier: Programming Language :: Python :: 3
Classifier: Programming Language :: Python :: 3.9
Classifier: Programming Language :: Python :: 3.10
Classifier: Programming Language :: Python :: 3.11
Requires-Dist: pre-commit (>=3.3.2,<4.0.0)
Requires-Dist: pyspark (>=3.4.0,<4.0.0)
